doitlive/__init__.py
doitlive/cli.py
doitlive/exceptions.py
doitlive/keyboard.py
doitlive/python_consoles.py
doitlive/styling.py
doitlive/termutils.py
doitlive/version_control.py
doitlive/ipython/__init__.py
doitlive/ipython/app.py
doitlive-5.1.0.dist-info/entry_points.txt
doitlive-5.1.0.dist-info/LICENSE
doitlive-5.1.0.dist-info/WHEEL
doitlive-5.1.0.dist-info/METADATA
doitlive-5.1.0.dist-info/RECORD
