Metadata-Version: 2.1
Name: doitlive
Version: 5.1.0
Summary: Because sometimes you need to do it live.
Keywords: doitlive,cli,live,coding,presentations,shell
Author-email: Steven Loria <sloria1@gmail.com>
Requires-Python: >=3.8
Classifier: Intended Audience :: Developers
Classifier: License :: OSI Approved :: MIT License
Classifier: Natural Language :: English
Classifier: Programming Language :: Python :: 3
Classifier: Programming Language :: Python :: 3.8
Classifier: Programming Language :: Python :: 3.9
Classifier: Programming Language :: Python :: 3.10
Classifier: Programming Language :: Python :: 3.11
Classifier: Programming Language :: Python :: 3.12
Classifier: Environment :: Console
Requires-Dist: click>=8.0,<9
Requires-Dist: click-completion>=0.3.1
Requires-Dist: click-didyoumean>=0.0.3
Requires-Dist: doitlive[tests] ; extra == "dev"
Requires-Dist: tox ; extra == "dev"
Requires-Dist: pre-commit~=3.6 ; extra == "dev"
Requires-Dist: sphinx==7.2.6 ; extra == "docs"
Requires-Dist: sphinx-issues==4.0.0 ; extra == "docs"
Requires-Dist: pytest ; extra == "tests"
Requires-Dist: IPython>=8 ; extra == "tests"
Project-URL: Issues, https://github.com/sloria/doitlive/issues
Project-URL: Source, https://github.com/sloria/doitlive/
Provides-Extra: dev
Provides-Extra: docs
Provides-Extra: tests
